<?xml version="1.0" encoding="utf-8"?>
<List>
  <Item Caption="Зямля з космасу" FileName="1"/>
  <Item Caption="Фотаздымак Сонца, зроблены праз адмысловы фільтр" FileName="2"/>
  <Item Caption="Марс" FileName="3"/>
  <Item Caption="Камэта" FileName="4"/>
  <Item Caption="Найбуйнейшы метэарытны кратэр. Арызона, ЗША" FileName="5"/>
  <Item Caption="Выгляд Зямлі з космасу" FileName="6"/>
  <Item Caption="Выгляд Зямлі з паверхні Месяца" FileName="7"/>
  <Item Caption="Сузор'е Шалі з атласа зорнага неба Яна Гавэл" FileName="8"/>
  <Item Caption="Сузор'е Льва з атласа зорнага неба Яна Гавэл" FileName="9"/>
  <Item Caption="Арбітальная станцыя ў касмічнай прасторы" FileName="10"/>
  <Item Caption="Чалавек на Месяцы" FileName="11"/>
  <Item Caption="Чалавек на Месяцы" FileName="12"/>
  <Item Caption="Ракета''Восток''на старце" FileName="13"/>
  <Item Caption="Першы касманаўт незалежнай Украіны Л. Каденюк" FileName="14"/>
  <Item Caption="Старт шматразовага корабля''Коламбия''" FileName="15"/>
  <Item Caption="Універсальная арбітальная станцыя, створаная айчыннымі ВО''Южмаш''и КБ''Южное''" FileName="16"/>
  <Item Caption="Зямля з космасу" FileName="17"/>
</List>
