<?xml version="1.0" encoding="UTF-8"?>
<testing name="ЗЕМЛЯ НА ПЛАНЕ И КАРТЕ">
  <question level="1" simple="True" text="Что в переводе с латинского означает слово &quot;глобус&quot;?">
    <answer flag="1" text="Пуля"/>
    <answer flag="0" text="Макет"/>
    <answer flag="0" text="Модель"/>
    <answer flag="0" text="Землеподобных"/>
  </question>
  <question level="1" simple="True" text="Как на глобусе или карте называется сетка меридианов и параллелей?">
    <answer flag="0" text="Параллельная"/>
    <answer flag="0" text="Прямоугольная"/>
    <answer flag="0" text="Меридианная"/>
    <answer flag="1" text="Градусная"/>
  </question>
  <question level="1" simple="True" text="Как называется воображаемая линия на поверхности Земли, равноудалена от полюсов?">
    <answer flag="1" text="Экватор"/>
    <answer flag="0" text="Меридиан"/>
    <answer flag="0" text="Тропик"/>
  </question>
  <question level="1" simple="True" text="Что является началом отсчета географической широты?">
    <answer flag="0" text="Северный полюс"/>
    <answer flag="0" text="Южный полюс"/>
    <answer flag="1" text="Экватор"/>
    <answer flag="0" text="Гринвичского меридиан"/>
  </question>
  <question level="1" simple="True" text="Какие утверждения являются правильными?">
    <answer flag="1" text="Экватор - самая длинная параллель"/>
    <answer flag="1" text="От Гринвичского меридиана осуществляется отсчет географической долготы"/>
    <answer flag="0" text="Длина всех параллелей увеличивается в направлении от экватора к полюсам"/>
  </question>
  <question level="1" simple="True" text="Какие точки на земной поверхности не имеют географической долготы?">
    <answer flag="0" text="Расположенные на Гринвичского меридиане"/>
    <answer flag="1" text="Расположенные на экваторе"/>
    <answer flag="0" text="Географические полюса Земли"/>
    <answer flag="0" text="Магнитные полюса Земли"/>
  </question>
  <question level="1" simple="True" text="Какие из признаков указывают на север?">
    <answer flag="1" text="Мох на одной стороне ствола"/>
    <answer flag="0" text="Более пологий склон муравейника"/>
    <answer flag="1" text="Короче ветви с одной стороны дерева, чем с другой"/>
    <answer flag="1" text="Полярная звезда"/>
  </question>
  <question level="1" simple="True" text="В направлении всегда указывает стрелка компаса?">
    <answer flag="0" text="В сторону Северного географического полюса Земли"/>
    <answer flag="1" text="В сторону Северного магнитного полюса Земли"/>
    <answer flag="0" text="В сторону Южного географического полюса Земли"/>
    <answer flag="0" text="В сторону Южного магнитного полюса Земли"/>
  </question>
  <question level="1" simple="True" text="Если стать лицом к югу, то">
    <answer flag="1" text="сзади будет север"/>
    <answer flag="0" text="справа будет восток"/>
    <answer flag="1" text="восток будет слева"/>
  </question>
  <question level="1" simple="True" text="Как правильно определить азимут?">
    <answer flag="0" text="От южного направления к любому предмету за ходом часовой стрелки"/>
    <answer flag="0" text="От южного направления к любому предмету против хода часовой стрелки"/>
    <answer flag="1" text="От северного направления к любому предмету за ходом часовой стрелки"/>
    <answer flag="0" text="От северного направления к любому предмету против хода часовой стрелки"/>
  </question>
  <question level="1" simple="True" text="Какие из азимутов определены правильно?">
    <answer flag="1" text="Азимут южного направления составляет 180 °"/>
    <answer flag="1" text="Азимут северного направления составляет 0 °"/>
    <answer flag="1" text="Азимут восточного направления составляет 90 °"/>
    <answer flag="0" text="Азимут западного направления составляет 360 °"/>
  </question>
  <question level="1" simple="True" text="Как должен быть ориентирован планшет при глазомерные съем?">
    <answer flag="0" text="Верхним краем на юг"/>
    <answer flag="1" text="Верхним краем на север"/>
    <answer flag="0" text="Верхним краем восток"/>
    <answer flag="0" text="Произвольно"/>
  </question>
  <question level="1" simple="True" text="Как называется высота объекта над уровнем моря?">
    <answer flag="0" text="Относительная высота"/>
    <answer flag="0" text="Условная высота"/>
    <answer flag="1" text="Абсолютная высота"/>
  </question>
  <question level="1" simple="True" text="Какие утверждения являются неправильными?">
    <answer flag="0" text="На карте территория изображается несколько искаженной"/>
    <answer flag="1" text="На одном плане можно изобразить всю поверхность Земли"/>
    <answer flag="1" text="На карте территория изображена точнее чем на плане"/>
    <answer flag="1" text="На плане можно изобразить большую территорию чем на карте"/>
  </question>
  <question level="1" simple="True" text="Как называют масштаб, записанное в виде дробного числа, числитель которой единица, а знаменатель - число, указывающее во сколько раз уменьшено изображение?">
    <answer flag="0" text="Именуемым"/>
    <answer flag="0" text="Дробным"/>
    <answer flag="1" text="Числовым или численным"/>
    <answer flag="0" text="Графическим"/>
  </question>
  <question level="1" simple="True" text="Карты, 1 см которых соответствует до 2 км на местности, относятся к категории">
    <answer flag="0" text="среднемасштабных"/>
    <answer flag="1" text="крупномасштабных"/>
    <answer flag="0" text="мелкомасштабных"/>
  </question>
  <question level="1" simple="True" text="Какое утверждение является неправильным?">
    <answer flag="1" text="План учитывает шарообразную форму Земли"/>
    <answer flag="0" text="Карта учитывает шарообразную форму Земли"/>
    <answer flag="0" text="Чем больше знаменатель масштаба, тем мельче масштаб"/>
  </question>
  <question level="1" simple="True" text="На сколько основных групп делятся все условные знаки топографических планов и карт?">
    <answer flag="1" text="4"/>
    <answer flag="0" text="на 2"/>
    <answer flag="0" text="5"/>
    <answer flag="0" text="на 3"/>
  </question>
  <question level="1" simple="True" text="Какие утверждения являются правильными?">
    <answer flag="1" text="Контурные условные знаки передают истинную форму объекта"/>
    <answer flag="1" text="Линейные условные знаки длину объекта передают в масштабе"/>
    <answer flag="0" text="Чем крупнее масштаб, тем больше знаменатель масштаба"/>
  </question>
  <question level="1" simple="True" text="Значковые условные знаки">
    <answer flag="0" text="передают истинную форму и размеры объекта в масштабе плана"/>
    <answer flag="0" text="используют для изображения линейных объектов"/>
    <answer flag="1" text="применяются тогда, когда форма объекта, через свой малый размер, не может быть отражена в масштабе"/>
  </question>
  <question level="1" simple="True" text="Чему равна знаменатель масштаба, если 1 см карты соответствует 100 м на местности?">
    <answer flag="0" text="100"/>
    <answer flag="0" text="1000"/>
    <answer flag="1" text="10 000"/>
  </question>
  <question level="1" simple="True" text="Горизонтали это">
    <answer flag="0" text="линии, соединяющие точки местности с одинаковой относительной высотой"/>
    <answer flag="0" text="линии, соединяющие высокие точки местности"/>
    <answer flag="1" text="линии, соединяющие точки местности с одинаковой абсолютной высотой"/>
  </question>
  <question level="1" simple="True" text="Что является признаком значительного крутизны склона на карте?">
    <answer flag="0" text="Горизонтали располагаются далеко друг от друга"/>
    <answer flag="0" text="Горизонтали очень извилисты"/>
    <answer flag="1" text="Горизонтали располагаются близко друг от друга"/>
  </question>
  <question level="1" simple="True" text="Как правильно размещать бергштрихи на карте?">
    <answer flag="0" text="Свободным концом в сторону повышения рельефа"/>
    <answer flag="1" text="Свободным концом в сторону понижения рельефа"/>
    <answer flag="0" text="Всегда свободным концом в направлении ближайшего моря"/>
  </question>
</testing>
