<?xml version="1.0" encoding="utf-8"?>
<List Title="Печерская лавра">
  <Item Caption="Позолоченные купола Киево-Печерской лавры" FileName="1"/>
  <Item Caption="Киево-Печерская лавра" FileName="2"/>
  <Item Caption="Учредители Печерского монастыря. Фрагменты иконы конца XI - начала XII в." FileName="3"/>
  <Item Caption="Золотая пектораль (нагрудное украшение) скифского царя - известный экспонат Музея исторических драгоценностей" FileName="4"/>
  <Item Caption="Один из подземных коридоров Ближних пещер" FileName="5"/>
  <Item Caption="В Ближних пещерах" FileName="6"/>
  <Item Caption="Церковь Св. Антония и Феодосия с трапезной" FileName="7"/>
  <Item Caption="Внутренний вид церкви Св. Антония и Феодосия" FileName="8"/>
  <Item Caption="Церковь Всех Святых над Экономическими воротами" FileName="9"/>
  <Item Caption="Вид на Днепр с Большой колокольни Киево-Печерской лавры" FileName="10"/>
  <Item Caption="В Киево-Печерской лавре" FileName="11"/>
  <Item Caption="В Киево-Печерской лавре" FileName="12"/>
</List>
