<?xml version="1.0" encoding="utf-8"?>
<List>
  <Item Caption="Ukrainian Carpathians. 1924" FileName="01"/>
  <Item Caption="Metropolitan Andriy" FileName="02"/>
  <Item Caption="Prayer. Western Ukraine, 1936" FileName="03"/>
  <Item Caption="Ukrainian patriotic cards" FileName="04"/>
  <Item Caption="Joseph Pilsudski" FileName="05"/>
  <Item Caption="Eugene Konovalets" FileName="06"/>
  <Item Caption="Stepan Bandera" FileName="07"/>
  <Item Caption="Shukhevych" FileName="08"/>
  <Item Caption="Andrew Miller" FileName="09"/>
  <Item Caption="Augustin Voloshin" FileName="10"/>
  <Item Caption="Augustin Voloshin" FileName="11"/>
</List>
