<?xml version="1.0" encoding="utf-8"?>
<List>
  <Item Caption="Lute days in 1917 in Kiev" FileName="01"/>
  <Item Caption="The manifestation of Sophia Square. Kyiv, 1917" FileName="02"/>
  <Item Caption="On the streets of Kyiv during the February Revolution" FileName="03"/>
  <Item Caption="Kyiv in March 1917" FileName="04"/>
  <Item Caption="Demonstration in Kharkov. April 1917" FileName="05"/>
  <Item Caption="Toppling the monument P. Stolypin. Kyiv, March 1917" FileName="06"/>
  <Item Caption="On the streets of Kyiv during the February Revolution" FileName="07"/>
  <Item Caption="Poster 1917" FileName="08"/>
  <Item Caption="Demonstration in Kharkov. 1917" FileName="09"/>
  <Item Caption="Demonstration in the Alexander" FileName="10"/>
  <Item Caption="Demonstration in Kharkov. 1917" FileName="11"/>
  <Item Caption="Kyiv in March 1917" FileName="12"/>
  <Item Caption="Returning from the front. Kyiv, 1917" FileName="13"/>
  <Item Caption="Hrushevsky" FileName="14"/>
  <Item Caption="Central House of the Parliament in Kiev" FileName="15"/>
  <Item Caption="General Secretariat of the Ukrainian Central Rada" FileName="16"/>
  <Item Caption="Vynnychenko" FileName="17"/>
  <Item Caption="Borys Martos" FileName="18"/>
  <Item Caption="Simon Petliura" FileName="19"/>
  <Item Caption="Nicholas Mikhnovskyy" FileName="20"/>
  <Item Caption="Soldier's rally. 1917" FileName="21"/>
  <Item Caption="Revolutionary soldiers. Kyiv, May 1917" FileName="22"/>
  <Item Caption="Revolutionary soldiers. Kyiv, 1917" FileName="23"/>
  <Item Caption="Detachment gunner. Ekaterinoslav, 1917" FileName="24"/>
  <Item Caption="Group of soldiers with revolutionary slogans. 1917" FileName="25"/>
  <Item Caption="Matros'kyi rally in Sevastopol. May 1917" FileName="26"/>
  <Item Caption="Revolutionary soldiers. 1917" FileName="27"/>
  <Item Caption="Members of the first Ukrainian Peasant Congress. Kyiv, June 1917" FileName="28"/>
  <Item Caption="Arsenal Plant in Kyiv" FileName="29"/>
  <Item Caption="Red. 1918" FileName="30"/>
  <Item Caption="Sketches of arms of UNR" FileName="31"/>
  <Item Caption="Emblem and seal of the UPR" FileName="32"/>
  <Item Caption="Members of the first Cossack congress. Chyhyryn October 1917" FileName="33"/>
  <Item Caption="Proclamation of the Third Universal. Kyiv, November 1917" FileName="34"/>
  <Item Caption="&quot;Peace be with Ukraine.&quot; German poster 1918" FileName="35"/>
  <Item Caption="The signing of the Brest peace. 1918" FileName="36"/>
</List>
