<?xml version="1.0" encoding="utf-8"?>
<List>
  <Item Caption="Засідання Державної ради Російської імперії" FileName="1"/>
  <Item Caption="Імператор Микола II" FileName="2"/>
  <Item Caption="На металургійному заводі" FileName="3"/>
  <Item Caption="Криголам &quot;Єрмак&quot;" FileName="4"/>
  <Item Caption="На ткацькій фабриці" FileName="5"/>
  <Item Caption="Підприємство початку XX ст." FileName="6"/>
  <Item Caption="Текстильна фабрика" FileName="7"/>
  <Item Caption="Робітниче селище" FileName="8"/>
  <Item Caption="Текстильна фабрика" FileName="9"/>
  <Item Caption="Бурлаки на Волзі. З картини Рєпіна" FileName="10"/>
  <Item Caption="Паровоз" FileName="11"/>
  <Item Caption="Російський фабрикант" FileName="12"/>
  <Item Caption="Інженери і службовці" FileName="13"/>
  <Item Caption="Генерал Куропаткін, головнокомандувач Маньчжурською армією під час російсько-японської війни" FileName="14"/>
  <Item Caption="Генерал Стессель, керував обороною Порт-Артура під час російсько-японської війни" FileName="15"/>
  <Item Caption="Адмірал Макаров, командував Тихоокеанською ескадрою. Загинув під час російсько-японської війни" FileName="16"/>
  <Item Caption="Відступ російської армії з-під Порт-Артура" FileName="17"/>
  <Item Caption="Загибель російського флоту в Цусімській битві" FileName="18"/>
  <Item Caption="&quot;Ікони замість гвинтівок&quot;. Карикатура на поразку російської армії у війні з японцями" FileName="19"/>
  <Item Caption="Кривава неділя" FileName="20"/>
  <Item Caption="Придушення заворушень у Варшаві. Плакат" FileName="21"/>
  <Item Caption="Козаки на вулицях міста, 1905 р." FileName="22"/>
  <Item Caption="Жертви єврейського погрому" FileName="23"/>
  <Item Caption="Російські жандарми" FileName="24"/>
  <Item Caption="Російські жандарми" FileName="25"/>
  <Item Caption="Каторжанин у кайданах" FileName="26"/>
  <Item Caption="Петро Столипін" FileName="27"/>
  <Item Caption="Російська асигнація" FileName="28"/>
  <Item Caption="Санкт-Петербурзька біржа" FileName="29"/>
  <Item Caption="Микола II з дружиною" FileName="30"/>
</List>
