<?xml version="1.0" encoding="utf-8"?>
<List>
  <Item Caption="Портрет Ивана Сирко, реконструирован учеными по черепу" FileName="1"/>
  <Item Caption="Чертомлыкская. Современная реконструкция" FileName="2"/>
  <Item Caption="Запорожская Сечь" FileName="3"/>
  <Item Caption="Польский король Ян Собеский" FileName="4"/>
  <Item Caption="Казацкая рада на Сечи. Из рисунка XVII в." FileName="5"/>
  <Item Caption="Запорожцы пишут письмо турецкому султану. Картина И. Репина" FileName="6"/>
  <Item Caption="Памятник на могиле Ивана Сирко в селе Капуловке вблизи Чертомлицкой Сечи" FileName="7"/>
  <Item Caption="Печати Войска Запорожского Низового и запорожских паланок" FileName="8"/>
  <Item Caption="Икона Покрова Пресвятой Богородицы с изображением последнего кошевого атамана Петра Калнышевского" FileName="9"/>
</List>
