<?xml version="1.0" encoding="UTF-8"?>
<testing name="Ранні жалезны век на ўкраінскіх землях. Свет качэўнікаў">
  <question level="1" simple="True" text="Які народ першым сярод жыхароў Стэпу навучыўся вырабляць жалеза, пачаўшы жалезны век на нашых стэпавых прасторах?">
    <answer flag="1" text="Киммерийцы"/>
    <answer flag="0" text="Скіфы"/>
    <answer flag="0" text="Сарматы"/>
  </question>
  <question level="1" simple="True" text="Што адбылося раней?">
    <answer flag="1" text="Панаванне киммерийцев ў северопричерноморских стэпах"/>
    <answer flag="0" text="Уварванне сармацкіх плямёнаў у прычерноморскіх стэпе"/>
  </question>
  <question level="1" simple="True" text="Які народ даследчыкі называюць першымі качэўнікамі на ўкраінскіх землях?">
    <answer flag="1" text="Киммерийцев"/>
    <answer flag="0" text="Скіфаў"/>
    <answer flag="0" text="Сарматаў"/>
  </question>
  <question level="1" simple="True" text="На які перыяд даводзіцца час росквіту скіфскага дзяржавы?">
    <answer flag="1" text="На 05/04 арт. да н. э"/>
    <answer flag="0" text="На 03/02 арт. да н.э."/>
  </question>
  <question level="1" simple="True" text="Якія тэрыторыі пакарыў сваёй улады цар Атей ў часы найвышэйшага ўздыму Вялікай Скіфіі?">
    <answer flag="1" text="Зямлі ад Дуная да Дона"/>
    <answer flag="0" text="Зямлі ад Днястра да Дняпра"/>
  </question>
  <question level="1" simple="True" text="Якія скіфскія плямёны панавалі ў Вялікай Скіфіі, заваяваўшы іншыя плямёны?">
    <answer flag="1" text="Скіфы-аратыя і скіфы-земляробы"/>
    <answer flag="0" text="Скіфы-качэўнікі і царскія скіфы"/>
  </question>
  <question level="1" simple="True" text="Дзе былі знойдзеныя знакамітую залатую пектораль 4 арт. да н.э., якая належала скіфскага цара?">
    <answer flag="0" text="У кургане Чертомлык на Днепропетровщине"/>
    <answer flag="1" text="У кургане Тоўстая Магіла на Днепропетровщине"/>
    <answer flag="0" text="У кургане Солоха на Запарожжа"/>
  </question>
  <question level="1" simple="True" text="Што ляжала ў аснове гаспадаркі скіфаў?">
    <answer flag="1" text="Развядзенне коней, буйнога і дробнага быдла і розныя промыслы, гандаль з антычнымі гарадамі, рабавання і даніна суседніх плямёнаў"/>
    <answer flag="0" text="Вырошчванне збожжа, вінаграду, гародніны, рыбалоўства і перапрацоўка рыбы і рамеснае вытворчасць"/>
  </question>
  <question level="1" simple="True" text="Якім зброяй карысталіся скіфы падчас ваенных дзеянняў?">
    <answer flag="1" text="Складаным дальнабойныя лукам і кароткімі і доўгімі мячамі"/>
    <answer flag="0" text="Шаблямі і муроломнимы машынамі-таранам"/>
  </question>
  <question level="1" simple="True" text="Хто з вядомых грэцкіх гісторыкаў прысвяціў скіфам кнігу сваіх даследаванняў, у якой апісаў іх тэрыторыю, заняткі, побыт, звычаі, рэлігію і паход супраць іх персідскага цара Дарыя І?">
    <answer flag="0" text="Гіпакрат"/>
    <answer flag="1" text="Герадот"/>
  </question>
  <question level="1" simple="True" text="Якога качавым народу саступілі скіфы, страціўшы панавальнае становішча ва ўкраінскіх стэпах?">
    <answer flag="0" text="Киммерийцам"/>
    <answer flag="1" text="Сарматаў"/>
    <answer flag="0" text="Готам"/>
  </question>
  <question level="1" simple="True" text="Колькі працягвалася валадарства сарматаў ў прычерноморскіх стэпах?">
    <answer flag="0" text="Амаль 200 гадоў"/>
    <answer flag="1" text="Амаль 600 гадоў"/>
  </question>
</testing>
