<?xml version="1.0" encoding="UTF-8"?>
<testing name="Украинские земли в составе Венгрии, Молдавии и Московского государства. Крым и украинское Причерноморье">
  <question level="1" simple="True" text="Кому принадлежали причерноморские степи перед монгольским нашествием?">
    <answer flag="1" text="Половцам"/>
    <answer flag="0" text="Монголам"/>
  </question>
  <question level="1" simple="True" text="Кто и когда стал первым правителем Крымского ханства, которое образовалось в результате распада Золотой Орды?">
    <answer flag="0" text="Штефан III в 1457 г."/>
    <answer flag="1" text="Хаджи-Гирей в 1449"/>
  </question>
  <question level="1" simple="True" text="Как называлась первая генуэзская колония в Северном Причерноморье, захваченная в 1475 году турецким султаном?">
    <answer flag="1" text="Кафа"/>
    <answer flag="0" text="Мангуп"/>
  </question>
  <question level="1" simple="True" text="Когда крымский хан Менгли-Гирей признал верховенство турецкого султана?">
    <answer flag="1" text="В 1478 г."/>
    <answer flag="0" text="В 1482 г."/>
  </question>
  <question level="1" simple="True" text="К какому городу пришли орды крымского хана Менгли-Гирея в первую великого похода на Украину?">
    <answer flag="1" text="В Киев"/>
    <answer flag="0" text="Во Львов"/>
  </question>
  <question level="1" simple="True" text="Имевших целью походы крымских орд на украинские земли?">
    <answer flag="0" text="Захват земель и присоединения к Крымского ханства"/>
    <answer flag="1" text="Разрушение, грабежи, захват пленников в плен"/>
  </question>
  <question level="1" simple="True" text="Какой литовский князь властвовал в Закарпатье, много сделав для развития края?">
    <answer flag="1" text="Федор Кориатович"/>
    <answer flag="0" text="Владимир Ольгердович"/>
  </question>
  <question level="1" simple="True" text="Между какими государствами были разделены Закарпатье после поражения венгерского войска от турок в битве при Могачем в 1526 г.?">
    <answer flag="0" text="Между Литовским княжеством и Московским царством"/>
    <answer flag="1" text="Между княжеством Трансильванией и Священной Римской империей, в которой правили императоры из австрийской династии Габсбургов"/>
  </question>
  <question level="1" simple="True" text="В составе какого государства находилась Буковина в XV века?">
    <answer flag="1" text="В составе Молдавского княжества"/>
    <answer flag="0" text="В составе Венгерского королевства"/>
  </question>
  <question level="1" simple="True" text="Какие земли потеряло Великое княжество Литовское в войнах против Московии до 1537 г.?">
    <answer flag="1" text="Чернигово-Сиверщину и Смоленск"/>
    <answer flag="0" text="Галицию и Волынь"/>
  </question>
  <question level="1" simple="True" text="Что произошло раньше?">
    <answer flag="1" text="Окончательная ликвидация Киевского удельного княжества и превращение его в воеводство Великого княжества Литовского"/>
    <answer flag="0" text="Признание Крымским ханством превосходства Османской империи"/>
  </question>
  <question level="1" simple="True" text="Кто возглавлял войска Великого княжества Литовского в победной битве под Оршей 1514 против Московии?">
    <answer flag="1" text="Константин Острожский"/>
    <answer flag="0" text="Андрей Барула"/>
  </question>
</testing>
