<?xml version="1.0" encoding="utf-8"?>
<List>
  <Item Caption="Kyiv princes and boyars" FileName="291"/>
  <Item Caption="Prince's marriage" FileName="309"/>
  <Item Caption="Kniazhychi" FileName="311"/>
  <Item Caption="Seal Vsevolod Yaroslavych" FileName="134"/>
  <Item Caption="Russians march on wives Polovtsi" FileName="130"/>
  <Item Caption="Rus Polovtsov taken captive. Drawing from the chronicle" FileName="128"/>
  <Item Caption="Kiyani 12 century." FileName="277"/>
  <Item Caption="Gold Medallion-coil Vladimir Monomakh" FileName="133"/>
  <Item Caption="Lubech lock. Reconstruction" FileName="129"/>
  <Item Caption="Autograph graffiti Vladimir Monomakh in St. Sophia Cathedral" FileName="197"/>
  <Item Caption="Diploma Mstislav Vladimirovich" FileName="137"/>
</List>
