<?xml version="1.0" encoding="utf-8"?>
<List>
  <Item Caption="Wealthy farmers, 12 cent." FileName="265"/>
  <Item Caption="Princely wife in a campaign" FileName="140"/>
  <Item Caption="The city of Vladimir in Kiev in early 13 century." FileName="141"/>
  <Item Caption="Kiev ANDERSON" FileName="299"/>
  <Item Caption="Spinner" FileName="318"/>
  <Item Caption="Princely palace in Chernihiv. Reconstruction" FileName="139"/>
  <Item Caption="Battle of the Rus Polovtsy" FileName="142"/>
  <Item Caption="Princess" FileName="300"/>
</List>
