<?xml version="1.0" encoding="UTF-8"?>
<testing name="Запорозька Січ у другій половині XVII ст.">
  <question level="1" simple="True" text="Як в історичній літературі називають Запорозьку Січ, що існувала в 1652—1709 рр.? ">
    <answer flag="0" text="Микитинська"/>
    <answer flag="1" text="Чортомлицька"/>
    <answer flag="0" text="Томаківська"/>
  </question>
  <question level="1" simple="True" text="На якій Січі розгорнув Богдан Хмельницький підготовку Національно-визвольної війни проти Речі Посполитої?">
    <answer flag="1" text="Микитинській"/>
    <answer flag="0" text="Чортомлицькій"/>
    <answer flag="0" text="Томаківській"/>
  </question>
  <question level="1" simple="True" text="Яка з подій збіглися в часі з існуванням Чортомлицької Січі?">
    <answer flag="0" text="Національно-визвольне повстання на чолі з П. Павлюком, Я. Острянином, Д. Гунею"/>
    <answer flag="1" text="Чигиринські походи об'єднаного турецько-татарського війська"/>
    <answer flag="0" text="Збаразько-Зборівська кампанія та укладення Зборівського договору між українцями та поляками"/>
  </question>
  <question level="1" simple="True" text="Кому з гетьманів допомогла здобути гетьманську булаву підтримка запорожців?">
    <answer flag="0" text="Петру Дорошенкові"/>
    <answer flag="1" text="Іванові Брюховецькому"/>
    <answer flag="0" text="Іванові Виговському"/>
  </question>
  <question level="1" simple="True" text="Який статус мала Запорозька Січ у складі Гетьманщини?">
    <answer flag="1" text="Запорозька Січ була окремою адміністративною одиницею"/>
    <answer flag="0" text="На Запорожжі було створено окремий Запорозький полк, очолюваний полковником"/>
  </question>
  <question level="1" simple="True" text="Під владою якої держави за &quot;Вічним миром&quot; мали перебувати землі Запорозької Січі?">
    <answer flag="1" text="Московського царства"/>
    <answer flag="0" text="Польщі"/>
    <answer flag="0" text="Османської імперії"/>
  </question>
  <question level="1" simple="True" text="Кого вважають найвидатнішим кошовим отаманом за всю історію існування Запорозьких Січей?">
    <answer flag="0" text="Богдана Хмельницького"/>
    <answer flag="1" text="Івана Сірка"/>
    <answer flag="0" text="Івана Брюховецького"/>
  </question>
  <question level="1" simple="True" text="У яких подіях брав безпосередню участь кошовий отаман Іван Сірко? ">
    <answer flag="1" text="Зречення Петром Дорошенком гетьманства в жовтні 1675 р."/>
    <answer flag="0" text="Козацька рада в Переяславі 1654 р."/>
    <answer flag="0" text="Перший Кримський похід 1687 р."/>
  </question>
  <question level="1" simple="True" text="З якою метою царський уряд розташовував на Січі свої залоги?">
    <answer flag="1" text="Царський уряд прагнув підкорити Січ, аби якнайповніше використати її військові та економічні можливості"/>
    <answer flag="0" text="Царський уряд прагнув здійснювати спільні походи московитів та запорожців проти Османської імперії для її загарбання"/>
  </question>
  <question level="1" simple="True" text="З ким безпосередньо підтримували торговельні контакти запорожці?">
    <answer flag="0" text="З мешканцями Західної України, польськими містами"/>
    <answer flag="1" text="З мешканцями Лівобережної України, московськими містами"/>
  </question>
  <question level="1" simple="True" text="Що продавали запорожці своїм торгівельним партнерам?">
    <answer flag="0" text="Хліб, а також зброю, боєприпаси, сукно, папір"/>
    <answer flag="1" text="Мед, шкури, хутро, рибу, віск, велику рогату худобу та коней"/>
  </question>
  <question level="1" simple="True" text="Де зараз розташована столиця запорозьких козаків часів Чортомлицької Січі?">
    <answer flag="0" text="На території сучасного міста Запоріжжя"/>
    <answer flag="1" text="Похована під водами штучного Каховського водосховища"/>
  </question>
</testing>
