<?xml version="1.0" encoding="utf-8"?>
<List>
  <Item Caption="Louis XI and Charles the Bold" FileName="02"/>
  <Item Caption="Charles the Bold, Duke of Burgundy" FileName="01"/>
  <Item Caption="Charles the Bold, Duke of Burgundy" FileName="128"/>
  <Item Caption="Fight against Switzerland, Charles the Bold" FileName="129"/>
  <Item Caption="Battle of Nancy. 1477" FileName="127"/>
  <Item Caption="Louis XI" FileName="125"/>
  <Item Caption="King Louis XII of France" FileName="138"/>
  <Item Caption="Payment of debts. France, XV century." FileName="129(1)"/>
  <Item Caption="Allegory of war between two roses in England XV. Painting of the XIX century." FileName="134"/>
</List>
