<?xml version="1.0" encoding="utf-8"?>
<List>
  <Item Caption="Хмельницкий" FileName="05"/>
  <Item Caption="Башни Старой крепости, г. Каменец-Подольский" FileName="02"/>
  <Item Caption="Костел св. Анны, 1607 г., г. Полонное" FileName="04"/>
  <Item Caption="Каньон на г. Смотрич в Каменец-Подольском" FileName="01"/>
  <Item Caption="Скала «Голова Витязя», с. Устье, Каменец-Подольский р-н" FileName="03"/>
  <Item Caption="Усадьба, XVIII века, с. Самчики, Староконстантиновский р-н" FileName="Hme_0"/>
  <Item Caption="Петропавловский костел XV века, г. Каменец-Подольский" FileName="Hme_19a"/>
  <Item Caption="Крепость, XI - XVII века, г. Каменец-Подольский" FileName="Hme_20"/>
  <Item Caption="Оборонительная башня замка, XVII - XVIII века, г. Староконстантинов" FileName="Hme_5a"/>
  <Item Caption="Церковь-замок Покрова Богородицы, XIV - XV века, с. Сутковцы, Ярмолинский р-н" FileName="Hme_d_1"/>
  <Item Caption="Замок, XIV - XVIII века, пгт Меджибож" FileName="Hme_d_10"/>
  <Item Caption="Башня замка, XV века, памятник Устиму Кармалюку, пгт Летичев" FileName="Hme_d_30"/>
</List>
